adh_sample_library_preview/ADHClient.py
adh_sample_library_preview/AbstractBaseClient.py
adh_sample_library_preview/AssetRules.py
adh_sample_library_preview/AssetTypes.py
adh_sample_library_preview/Assets.py
adh_sample_library_preview/Authentication.py
adh_sample_library_preview/AuthorizationTags.py
adh_sample_library_preview/BaseClient.py
adh_sample_library_preview/BaseClientStub.py
adh_sample_library_preview/Communities.py
adh_sample_library_preview/ContentResolvers.py
adh_sample_library_preview/DataViews.py
adh_sample_library_preview/EDSClient.py
adh_sample_library_preview/Enumerations.py
adh_sample_library_preview/EventTypes.py
adh_sample_library_preview/Events.py
adh_sample_library_preview/GraphQL.py
adh_sample_library_preview/Namespaces.py
adh_sample_library_preview/OCSClient.py
adh_sample_library_preview/PatchableSecurable.py
adh_sample_library_preview/ReferenceData.py
adh_sample_library_preview/ReferenceDataTypes.py
adh_sample_library_preview/Roles.py
adh_sample_library_preview/SdsError.py
adh_sample_library_preview/Securable.py
adh_sample_library_preview/SharedStreams.py
adh_sample_library_preview/Signups.py
adh_sample_library_preview/StreamViews.py
adh_sample_library_preview/Streams.py
adh_sample_library_preview/Subscriptions.py
adh_sample_library_preview/Topics.py
adh_sample_library_preview/Types.py
adh_sample_library_preview/Units.py
adh_sample_library_preview/Users.py
adh_sample_library_preview/__init__.py
adh_sample_library_preview/Asset/Asset.py
adh_sample_library_preview/Asset/AssetRule.py
adh_sample_library_preview/Asset/AssetType.py
adh_sample_library_preview/Asset/MetadataItem.py
adh_sample_library_preview/Asset/StreamReference.py
adh_sample_library_preview/Asset/TypeReference.py
adh_sample_library_preview/Asset/__init__.py
adh_sample_library_preview/Asset/Data/DataErrors.py
adh_sample_library_preview/Asset/Data/DataResults.py
adh_sample_library_preview/Asset/Data/__init__.py
adh_sample_library_preview/Asset/Resolved/ResolvedAsset.py
adh_sample_library_preview-0.10.19rc0.dist-info/LICENSE
adh_sample_library_preview-0.10.19rc0.dist-info/METADATA
adh_sample_library_preview-0.10.19rc0.dist-info/WHEEL
adh_sample_library_preview-0.10.19rc0.dist-info/top_level.txt
adh_sample_library_preview-0.10.19rc0.dist-info/RECORD
