Metadata-Version: 2.1
Name: adh-sample-library-preview
Version: 0.10.19rc0
Summary: A preview of an ADH (Aveva Data Hub) client library
Home-page: https://github.com/aveva/sample-adh-sample_libraries-python
Author: OSIsoft
Author-email: samples@osisoft.com
License: Apache 2.0
Platform: UNKNOWN
Classifier: Programming Language :: Python :: 3
Classifier: License :: OSI Approved :: Apache Software License
Classifier: Operating System :: OS Independent
Obsoletes: ocs_sample_library_preview
Requires-Python: >=3.7
License-File: LICENSE
Requires-Dist: jsonpatch (>=1.32)
Requires-Dist: python-dateutil (>=2.8.2)
Requires-Dist: requests (>=2.28.2)
Provides-Extra: test
Requires-Dist: pytest (>=7.0.1) ; extra == 'test'
